{
  "version": "v2",
  "uptime_seconds": 4500,
  "cycle_count": 322,
  "cycle_interval_sec": 10,
  "last_cycle_ts": "2026-03-21T17:44:32.128997+00:00",
  "trading_enabled": true,
  "dry_run": false,
  "kill_switch_armed": false,
  "config_snapshot": {
    "quantity": 1,
    "max_entry_cents": 40,
    "min_edge_cents": 8,
    "daily_loss_limit_cents": 500,
    "consecutive_loss_breaker": 5,
    "strategies": {
      "latency": false,
      "calibrated": false,
      "arbitrage": false,
      "predictor": false
    }
  },
  "total_pnl": 0.0,
  "pnl_today": 0.0,
  "win_rate": 0.0,
  "wins": 0,
  "losses": 0,
  "trades_today": 0,
  "signals_today": 230,
  "bankroll": 58.59,
  "exposure": 0.0,
  "open_positions": 0,
  "events": [],
  "last_signals": [],
  "positions": [],
  "markets": [],
  "prices": {
    "BTC": {
      "spot": 70389.92,
      "source": "coinbase"
    },
    "ETH": {
      "spot": 2149.93,
      "source": "kraken"
    }
  },
  "strategies": {
    "latency": 0,
    "calibrated": 0,
    "arbitrage": 0,
    "predictor": 0,
    "skipped": 0
  },
  "bankroll_history": [
    56.35,
    57.21,
    56.53,
    56.55,
    58.49
  ],
  "feed_status": {
    "kraken": {
      "ready": true,
      "stale": true,
      "btc_age": 18.9,
      "eth_age": 2.0,
      "btc": 70395.8,
      "eth": 2149.93
    },
    "binance": {
      "ready": true,
      "stale": false,
      "btc_age": 4.3,
      "eth_age": 7.9,
      "btc": 70403.21,
      "eth": 2150.28
    },
    "coinbase": {
      "ready": true,
      "stale": false,
      "btc_age": 2.4,
      "eth_age": 2.0,
      "btc": 70389.92,
      "eth": 2149.57
    },
    "active_source": {
      "BTC": "coinbase",
      "ETH": "kraken"
    }
  },
  "updated_at": "2026-03-21T17:44:32.129022+00:00"
}