{
  "version": "v2",
  "uptime_seconds": 2,
  "cycle_count": 0,
  "cycle_interval_sec": 10,
  "last_cycle_ts": "2026-03-21T02:08:19.045284+00:00",
  "trading_enabled": true,
  "dry_run": false,
  "kill_switch_armed": false,
  "config_snapshot": {
    "quantity": 1,
    "max_entry_cents": 35,
    "min_edge_cents": 5,
    "daily_loss_limit_cents": 500,
    "consecutive_loss_breaker": 5,
    "strategies": {
      "latency": true,
      "calibrated": true,
      "arbitrage": false
    }
  },
  "total_pnl": -1.0,
  "pnl_today": -1.0,
  "win_rate": 25.0,
  "wins": 1,
  "losses": 3,
  "trades_today": 0,
  "signals_today": 118,
  "bankroll": 58.4,
  "exposure": 0.0,
  "open_positions": 0,
  "events": [],
  "last_signals": [],
  "positions": [],
  "markets": [],
  "prices": {
    "BTC": {
      "spot": 70495.65,
      "source": "coinbase"
    },
    "ETH": {
      "spot": 2147.97,
      "source": "coinbase"
    }
  },
  "strategies": {
    "latency": 0,
    "calibrated": 0,
    "arbitrage": 0,
    "skipped": 0
  },
  "bankroll_history": [
    58.4
  ],
  "feed_status": {
    "kraken": {
      "ready": false,
      "stale": true,
      "btc_age": Infinity,
      "eth_age": Infinity,
      "btc": null,
      "eth": null
    },
    "binance": {
      "ready": false,
      "stale": true,
      "btc_age": Infinity,
      "eth_age": Infinity,
      "btc": null,
      "eth": null
    },
    "coinbase": {
      "ready": true,
      "stale": false,
      "btc_age": 1.8,
      "eth_age": 1.8,
      "btc": 70495.65,
      "eth": 2147.97
    },
    "active_source": {
      "BTC": "coinbase",
      "ETH": "coinbase"
    }
  },
  "updated_at": "2026-03-21T02:08:19.045296+00:00"
}